{
    "_links": {
        "self": {
            "href": "http:\/\/default\/sample-storyline?_format=hal_json"
        },
        "type": {
            "href": "http:\/\/drupal.org\/rest\/type\/node\/page"
        },
        "http:\/\/drupal.org\/rest\/relation\/node\/page\/revision_uid": [
            {
                "href": "http:\/\/default\/user\/1?_format=hal_json"
            }
        ],
        "http:\/\/drupal.org\/rest\/relation\/node\/page\/uid": [
            {
                "href": "http:\/\/default\/user\/1?_format=hal_json",
                "lang": "en"
            }
        ],
        "http:\/\/drupal.org\/rest\/relation\/node\/page\/field_body_paragraph": [
            {
                "href": "",
                "lang": "en"
            }
        ],
        "http:\/\/drupal.org\/rest\/relation\/node\/page\/field_storyline": [
            {
                "href": ""
            },
            {
                "href": ""
            },
            {
                "href": ""
            },
            {
                "href": ""
            },
            {
                "href": ""
            }
        ]
    },
    "uuid": [
        {
            "value": "fa23e4c5-894b-4777-90b4-ae2b5d51ba30"
        }
    ],
    "langcode": [
        {
            "value": "en",
            "lang": "en"
        }
    ],
    "type": [
        {
            "target_id": "page"
        }
    ],
    "revision_timestamp": [
        {
            "value": "2018-03-07T19:47:38+00:00",
            "format": "Y-m-d\\TH:i:sP"
        }
    ],
    "_embedded": {
        "http:\/\/drupal.org\/rest\/relation\/node\/page\/revision_uid": [
            {
                "_links": {
                    "self": {
                        "href": "http:\/\/default\/user\/1?_format=hal_json"
                    },
                    "type": {
                        "href": "http:\/\/drupal.org\/rest\/type\/user\/user"
                    }
                },
                "uuid": [
                    {
                        "value": "cf372aec-4cb7-41ae-8229-af134ed1d133"
                    }
                ]
            }
        ],
        "http:\/\/drupal.org\/rest\/relation\/node\/page\/uid": [
            {
                "_links": {
                    "self": {
                        "href": "http:\/\/default\/user\/1?_format=hal_json"
                    },
                    "type": {
                        "href": "http:\/\/drupal.org\/rest\/type\/user\/user"
                    }
                },
                "uuid": [
                    {
                        "value": "cf372aec-4cb7-41ae-8229-af134ed1d133"
                    }
                ],
                "lang": "en"
            }
        ],
        "http:\/\/drupal.org\/rest\/relation\/node\/page\/field_body_paragraph": [
            {
                "_links": {
                    "self": {
                        "href": ""
                    },
                    "type": {
                        "href": "http:\/\/drupal.org\/rest\/type\/paragraph\/text"
                    }
                },
                "uuid": [
                    {
                        "value": "88679e12-9b18-45d5-82aa-38ee5a368680"
                    }
                ],
                "lang": "en"
            }
        ],
        "http:\/\/drupal.org\/rest\/relation\/node\/page\/field_storyline": [
            {
                "_links": {
                    "self": {
                        "href": ""
                    },
                    "type": {
                        "href": "http:\/\/drupal.org\/rest\/type\/paragraph\/storyline_header"
                    }
                },
                "uuid": [
                    {
                        "value": "6b23cbbd-7876-47e9-86a1-ed557181e855"
                    }
                ]
            },
            {
                "_links": {
                    "self": {
                        "href": ""
                    },
                    "type": {
                        "href": "http:\/\/drupal.org\/rest\/type\/paragraph\/storyline_item"
                    }
                },
                "uuid": [
                    {
                        "value": "61be063c-4d97-4bbd-a154-a8d0548778c2"
                    }
                ]
            },
            {
                "_links": {
                    "self": {
                        "href": ""
                    },
                    "type": {
                        "href": "http:\/\/drupal.org\/rest\/type\/paragraph\/storyline_item"
                    }
                },
                "uuid": [
                    {
                        "value": "fa25c697-0451-4a85-b9a8-58bba61fa9fa"
                    }
                ]
            },
            {
                "_links": {
                    "self": {
                        "href": ""
                    },
                    "type": {
                        "href": "http:\/\/drupal.org\/rest\/type\/paragraph\/storyline_header"
                    }
                },
                "uuid": [
                    {
                        "value": "cd9b2142-f3b8-42e7-b8ad-dd21a993d33b"
                    }
                ]
            },
            {
                "_links": {
                    "self": {
                        "href": ""
                    },
                    "type": {
                        "href": "http:\/\/drupal.org\/rest\/type\/paragraph\/storyline_item"
                    }
                },
                "uuid": [
                    {
                        "value": "53ad0745-1b5c-4d73-866a-31bd078dba20"
                    }
                ]
            }
        ]
    },
    "status": [
        {
            "value": true,
            "lang": "en"
        }
    ],
    "title": [
        {
            "value": "Sample storyline",
            "lang": "en"
        }
    ],
    "created": [
        {
            "value": "2018-03-07T19:30:22+00:00",
            "lang": "en",
            "format": "Y-m-d\\TH:i:sP"
        }
    ],
    "changed": [
        {
            "value": "2018-03-07T19:47:38+00:00",
            "lang": "en",
            "format": "Y-m-d\\TH:i:sP"
        }
    ],
    "promote": [
        {
            "value": false
        }
    ],
    "sticky": [
        {
            "value": false,
            "lang": "en"
        }
    ],
    "default_langcode": [
        {
            "value": true,
            "lang": "en"
        }
    ],
    "revision_translation_affected": [
        {
            "value": true,
            "lang": "en"
        }
    ],
    "path": [
        {
            "alias": "\/sample-storyline",
            "pid": 41,
            "langcode": "en",
            "lang": "en"
        }
    ],
    "field_summary": [
        {
            "value": "<p>This is the summary which should provide a short description for your storyline. A storyline is a simple way to show a chronology or tell a story in a graphical format. A storyline can include specific dates but unlike some timelines does not require this, allowing you to organize in any manner you like.<\/p>\r\n",
            "format": "basic_html",
            "lang": "en"
        }
    ]
}
